{
	"$schema": "http://schema.management.azure.com/schemas/2015-01-01/deploymentTemplate.json#",
	"contentVersion": "1.0.0.0",
	"parameters": {
		"factoryName": {
			"type": "string",
			"metadata": "Data Factory name"
		},
		"linkedService_workspaceapi": {
			"type": "string"
		}
	},
	"variables": {
		"factoryId": "[concat('Microsoft.DataFactory/factories/', parameters('factoryName'))]"
	},
	"resources": [
		{
			"name": "[concat(parameters('factoryName'), '/activity')]",
			"type": "Microsoft.DataFactory/factories/pipelines",
			"apiVersion": "2018-06-01",
			"properties": {
				"activities": [
					{
						"name": "StartDate",
						"type": "SetVariable",
						"dependsOn": [],
						"userProperties": [],
						"typeProperties": {
							"variableName": "StartDate",
							"value": {
								"value": "@formatDateTime(adddays(utcnow(),pipeline().parameters.Day),'yyyy-MM-dd')",
								"type": "Expression"
							}
						}
					},
					{
						"name": "EndDate",
						"type": "SetVariable",
						"dependsOn": [],
						"userProperties": [],
						"typeProperties": {
							"variableName": "EndDate",
							"value": {
								"value": "@formatDateTime(adddays(utcnow(),pipeline().parameters.Day),'yyyy-MM-dd')",
								"type": "Expression"
							}
						}
					},
					{
						"name": "Execute Pipeline1",
						"type": "ExecutePipeline",
						"dependsOn": [
							{
								"activity": "Get Access Token",
								"dependencyConditions": [
									"Succeeded"
								]
							},
							{
								"activity": "StartDate",
								"dependencyConditions": [
									"Succeeded"
								]
							},
							{
								"activity": "EndDate",
								"dependencyConditions": [
									"Succeeded"
								]
							}
						],
						"userProperties": [],
						"typeProperties": {
							"pipeline": {
								"referenceName": "sub-activity",
								"type": "PipelineReference"
							},
							"waitOnCompletion": true,
							"parameters": {
								"Bearer_Token": {
									"value": "@activity('Get Access Token').access_token.value",
									"type": "Expression"
								},
								"startDateTime": {
									"value": "@concat('''',variables('StartDate'),'T00%3A00%3A00.000Z','''')",
									"type": "Expression"
								},
								"endDateTime": {
									"value": "@concat('''',variables('EndDate'),'2022-11-30T23%3A59%3A59%3A000Z','''')",
									"type": "Expression"
								}
							}
						}
					},
					{
						"name": "Get Access Token",
						"type": "WebActivity",
						"dependsOn": [],
						"policy": {
							"timeout": "0.12:00:00",
							"retry": 0,
							"retryIntervalInSeconds": 30,
							"secureOutput": false,
							"secureInput": false
						},
						"userProperties": [],
						"typeProperties": {
							"url": {
								"value": "https://login.microsoftonline.com/30bf9f37-d550-4878-9494-1041656caf27/oauth2/token",
								"type": "Expression"
							},
							"method": "POST",
							"headers": {
								"Content-Type": "application/x-www-form-urlencoded"
							},
							"body": {
								"value": "grant_type=client_credentials&client_id=5ff6eba2-c57c-4b25-a963-7383a8adc0e2&client_secret=X7d8Q~kh~4BYuKOEPrJsPS4-cv6sLKT0Un2klbqJ&resource=https://analysis.windows.net/powerbi/api\n",
								"type": "Expression"
							}
						}
					}
				],
				"parameters": {
					"Bearer_Token": {
						"type": "string"
					},
					"Day": {
						"type": "int",
						"defaultValue": -20
					}
				},
				"variables": {
					"StartDate": {
						"type": "String"
					},
					"EndDate": {
						"type": "String"
					}
				},
				"annotations": [],
				"lastPublishTime": "2022-12-01T06:27:53Z"
			},
			"dependsOn": [
				"[concat(variables('factoryId'), '/pipelines/sub-activity')]"
			]
		},
		{
			"name": "[concat(parameters('factoryName'), '/sub-activity')]",
			"type": "Microsoft.DataFactory/factories/pipelines",
			"apiVersion": "2018-06-01",
			"properties": {
				"activities": [
					{
						"name": "CT",
						"type": "SetVariable",
						"dependsOn": [],
						"userProperties": [],
						"typeProperties": {
							"variableName": "continuationToken",
							"value": {
								"value": "@concat('')",
								"type": "Expression"
							}
						}
					},
					{
						"name": "Flag",
						"type": "SetVariable",
						"dependsOn": [],
						"userProperties": [],
						"typeProperties": {
							"variableName": "Flag",
							"value": {
								"value": "@bool(1)",
								"type": "Expression"
							}
						}
					},
					{
						"name": "Until_CT_NULL",
						"type": "Until",
						"dependsOn": [
							{
								"activity": "Flag",
								"dependencyConditions": [
									"Succeeded"
								]
							},
							{
								"activity": "CT",
								"dependencyConditions": [
									"Succeeded"
								]
							}
						],
						"userProperties": [],
						"typeProperties": {
							"expression": {
								"value": "@equals(bool(1),variables('Flag'))",
								"type": "Expression"
							},
							"activities": [
								{
									"name": "Activity_Date_Url",
									"type": "WebActivity",
									"dependsOn": [],
									"policy": {
										"timeout": "0.12:00:00",
										"retry": 0,
										"retryIntervalInSeconds": 30,
										"secureOutput": false,
										"secureInput": false
									},
									"userProperties": [],
									"typeProperties": {
										"url": {
											"value": "@if(equals(variables('continuationToken'),''),concat('https://api.powerbi.com/v1.0/myorg/admin/activityevents?startDateTime=',pipeline().parameters.startDateTime,'&endDateTime=',pipeline().parameters.endDateTime),concat('https://api.powerbi.com/v1.0/myorg/admin/activityevents?continuationToken=''',variables('continuationToken'),''''))",
											"type": "Expression"
										},
										"method": "GET",
										"headers": {
											"Authorization": {
												"value": "@concat('Bearer ',pipeline().parameters.Bearer_Token)",
												"type": "Expression"
											}
										}
									}
								},
								{
									"name": "Execute_Activity_Data_Dump",
									"type": "ExecutePipeline",
									"dependsOn": [
										{
											"activity": "Activity_Date_Url",
											"dependencyConditions": [
												"Succeeded"
											]
										}
									],
									"userProperties": [],
									"typeProperties": {
										"pipeline": {
											"referenceName": "sub-sub-activity",
											"type": "PipelineReference"
										},
										"waitOnCompletion": true,
										"parameters": {
											"activityEventEntities": {
												"value": "@activity('Activity_Date_Url').output.activityEventEntities",
												"type": "Expression"
											}
										}
									}
								},
								{
									"name": "set_CT",
									"type": "SetVariable",
									"dependsOn": [
										{
											"activity": "Activity_Date_Url",
											"dependencyConditions": [
												"Succeeded"
											]
										}
									],
									"userProperties": [],
									"typeProperties": {
										"variableName": "continuationToken",
										"value": {
											"value": "@activity('Activity_Date_Url').output?.continuationToken",
											"type": "Expression"
										}
									}
								},
								{
									"name": "set_Flag",
									"type": "SetVariable",
									"dependsOn": [
										{
											"activity": "Activity_Date_Url",
											"dependencyConditions": [
												"Succeeded"
											]
										}
									],
									"userProperties": [],
									"typeProperties": {
										"variableName": "Flag",
										"value": {
											"value": "@if(equals(coalesce(activity('Activity_Date_Url').output.continuationToken,0),0),bool(0),bool(1))",
											"type": "Expression"
										}
									}
								}
							],
							"timeout": "0.12:00:00"
						}
					}
				],
				"parameters": {
					"Bearer_Token": {
						"type": "string"
					},
					"startDateTime": {
						"type": "string"
					},
					"endDateTime": {
						"type": "string"
					}
				},
				"variables": {
					"continuationToken": {
						"type": "String"
					},
					"Flag": {
						"type": "Boolean"
					}
				},
				"annotations": [],
				"lastPublishTime": "2022-12-01T05:55:27Z"
			},
			"dependsOn": [
				"[concat(variables('factoryId'), '/pipelines/sub-sub-activity')]"
			]
		},
		{
			"name": "[concat(parameters('factoryName'), '/sub-sub-activity')]",
			"type": "Microsoft.DataFactory/factories/pipelines",
			"apiVersion": "2018-06-01",
			"properties": {
				"activities": [
					{
						"name": "Each_Activity_Dump_Data",
						"type": "ForEach",
						"dependsOn": [],
						"userProperties": [],
						"typeProperties": {
							"items": {
								"value": "@pipeline().parameters.activityEventEntities",
								"type": "Expression"
							},
							"batchCount": 10,
							"activities": [
								{
									"name": "Activity_Data_Dump",
									"type": "SqlServerStoredProcedure",
									"dependsOn": [],
									"policy": {
										"timeout": "0.12:00:00",
										"retry": 0,
										"retryIntervalInSeconds": 30,
										"secureOutput": false,
										"secureInput": false
									},
									"userProperties": [],
									"typeProperties": {
										"storedProcedureName": "[[dbo].[Activity]",
										"storedProcedureParameters": {
											"Activity": {
												"value": {
													"value": "@item().Activity",
													"type": "Expression"
												},
												"type": "String"
											},
											"ActivityId": {
												"value": {
													"value": "@item().ActivityId",
													"type": "Expression"
												},
												"type": "String"
											},
											"AppName": {
												"value": {
													"value": "@item().AppName",
													"type": "Expression"
												},
												"type": "String"
											},
											"AppReportId": {
												"value": {
													"value": "@item().AppReportId",
													"type": "Expression"
												},
												"type": "String"
											},
											"CapacityId": {
												"value": {
													"value": "@item().CapacityId",
													"type": "Expression"
												},
												"type": "String"
											},
											"CapacityName": {
												"value": {
													"value": "@item().CapacityName",
													"type": "Expression"
												},
												"type": "String"
											},
											"ClientIP": {
												"value": {
													"value": "@item().ClientIP",
													"type": "Expression"
												},
												"type": "String"
											},
											"ConsumptionMethod": {
												"value": {
													"value": "@item().ConsumptionMethod",
													"type": "Expression"
												},
												"type": "String"
											},
											"CreationDate": {
												"value": {
													"value": "@item().CreationDate",
													"type": "Expression"
												},
												"type": "String"
											},
											"CreationTime": {
												"value": {
													"value": "@item().CreationTime",
													"type": "Expression"
												},
												"type": "String"
											},
											"DashboardId": {
												"value": {
													"value": "@item().DashboardId",
													"type": "Expression"
												},
												"type": "String"
											},
											"DataConnectivityMode": {
												"value": {
													"value": "@item().DataConnectivityMode",
													"type": "Expression"
												},
												"type": "String"
											},
											"DatasetId": {
												"value": {
													"value": "@item().DatasetId",
													"type": "Expression"
												},
												"type": "String"
											},
											"DatasetName": {
												"value": {
													"value": "@item().DatasetName",
													"type": "Expression"
												},
												"type": "String"
											},
											"DistributionMethod": {
												"value": {
													"value": "@item().DistributionMethod",
													"type": "Expression"
												},
												"type": "String"
											},
											"Id": {
												"value": {
													"value": "@item().Id",
													"type": "Expression"
												},
												"type": "String"
											},
											"ImportDisplayName": {
												"value": {
													"value": "@item().ImportDisplayName",
													"type": "Expression"
												},
												"type": "String"
											},
											"ImportId": {
												"value": {
													"value": "@item().ImportId",
													"type": "Expression"
												},
												"type": "String"
											},
											"ImportSource": {
												"value": {
													"value": "@item().ImportSource",
													"type": "Expression"
												},
												"type": "String"
											},
											"ImportType": {
												"value": {
													"value": "@item().ImportType",
													"type": "Expression"
												},
												"type": "String"
											},
											"IsSuccess": {
												"value": {
													"value": "@item().IsSuccess",
													"type": "Expression"
												},
												"type": "String"
											},
											"ItemName": {
												"value": {
													"value": "@item().ItemName",
													"type": "Expression"
												},
												"type": "String"
											},
											"LastRefreshTime": {
												"value": {
													"value": "@item().LastRefreshTime",
													"type": "Expression"
												},
												"type": "String"
											},
											"ObjectId": {
												"value": {
													"value": "@item().ObjectId",
													"type": "Expression"
												},
												"type": "String"
											},
											"Operation": {
												"value": {
													"value": "@item().Operation",
													"type": "Expression"
												},
												"type": "String"
											},
											"OrganizationId": {
												"value": {
													"value": "@item().OrganizationId",
													"type": "Expression"
												},
												"type": "String"
											},
											"RecordType": {
												"value": {
													"value": "@item().RecordType",
													"type": "Expression"
												},
												"type": "String"
											},
											"ReportId": {
												"value": {
													"value": "@item().ReportId",
													"type": "Expression"
												},
												"type": "String"
											},
											"ReportName": {
												"value": {
													"value": "@item().ReportName",
													"type": "Expression"
												},
												"type": "String"
											},
											"ReportType": {
												"value": {
													"value": "@item().ReportType",
													"type": "Expression"
												},
												"type": "String"
											},
											"RequestId": {
												"value": {
													"value": "@item().RequestId",
													"type": "Expression"
												},
												"type": "String"
											},
											"RetrieveDate": {
												"value": {
													"value": "@item().RetrieveDate",
													"type": "Expression"
												},
												"type": "String"
											},
											"UserAgent": {
												"value": {
													"value": "@item().UserAgent",
													"type": "Expression"
												},
												"type": "String"
											},
											"UserId": {
												"value": {
													"value": "@item().UserId",
													"type": "Expression"
												},
												"type": "String"
											},
											"UserKey": {
												"value": {
													"value": "@item().UserKey",
													"type": "Expression"
												},
												"type": "String"
											},
											"UserType": {
												"value": {
													"value": "@item().UserType",
													"type": "Expression"
												},
												"type": "String"
											},
											"Workload": {
												"value": {
													"value": "@item().Workload",
													"type": "Expression"
												},
												"type": "String"
											},
											"WorkspaceId": {
												"value": {
													"value": "@item().WorkspaceId",
													"type": "Expression"
												},
												"type": "String"
											},
											"WorkSpaceName": {
												"value": {
													"value": "@item().WorkSpaceName",
													"type": "Expression"
												},
												"type": "String"
											}
										}
									},
									"linkedServiceName": {
										"referenceName": "[parameters('linkedService_workspaceapi')]",
										"type": "LinkedServiceReference"
									}
								}
							]
						}
					}
				],
				"parameters": {
					"activityEventEntities": {
						"type": "array"
					}
				},
				"annotations": [],
				"lastPublishTime": "2022-11-17T15:07:56Z"
			},
			"dependsOn": []
		}
	]
}